{
    "4 23 2025": {
        "importantArticles": [
            {
                "headline": "We recently published a list of the 12 Best Stocks Under $100 to Buy According to Hedge Funds. In this article, we are going to take a look at where Citigroup Inc. (NYSE:C) stands against other stocks under $100 to buy according to hedge funds. On April 21, Chris Davis of Davis Advisors appeared on [\u2026]",
                "publication_date": "2025-04-23T00:00:00.000Z",
                "sentiment": "Positive",
                "sentimentScore": "0.6369",
                "source": "Insider Monkey",
                "ticker": "C",
                "title": "Is Citigroup Inc. (NYSE:C) the Best Stock Under $100 to Buy According to Hedge Funds?",
                "url": "https://finance.yahoo.com/news/citigroup-inc-nyse-c-best-160910853.html"
            },
            {
                "headline": "(Bloomberg) -- US stocks jumped, wiping out Monday\u2019s plunge, as traders unleashed risky bets that the White House will clinch crucial trade deals with top economic partners. The dollar recovered slightly from Monday\u2019s lows while short-term Treasury yields climbed.Most Read from BloombergTrump Gives New York \u2018One Last Chance\u2019 to End Congestion FeeDOGE Visits National Gallery of Art to Discuss Museum\u2019s Legal StatusThe Racial Wealth Gap Is Not Just About MoneyThe S&P 500 rose 2.5% \u2014 notching its be",
                "publication_date": "2025-04-23T00:00:00.000Z",
                "sentiment": "Positive",
                "sentimentScore": "0.6077",
                "source": "Bloomberg",
                "ticker": "C",
                "title": "US Stocks Rebound as Traders Regain Risk Appetite: Markets Wrap",
                "url": "https://finance.yahoo.com/news/asian-stocks-drop-us-selloff-003202089.html"
            },
            {
                "headline": "(Bloomberg) -- Traders have long known Donald Trump intended to use tariffs as a tool for economic policy. Citigroup Inc., a year ago, even offered up a handy framework for trading potential levies on China.Most Read from BloombergTrump Gives New York \u2018One Last Chance\u2019 to End Congestion FeeDOGE Visits National Gallery of Art to Discuss Museum\u2019s Legal StatusThe Racial Wealth Gap Is Not Just About MoneyWhy Car YouTuber Matt Farah Is Fighting for Walkable CitiesBackyard Micro-Flats Aim to Ease Sout",
                "publication_date": "2025-04-23T00:00:00.000Z",
                "sentiment": "Positive",
                "sentimentScore": "0.5719",
                "source": "Bloomberg",
                "ticker": "C",
                "title": "You Can\u2019t\u00a0Out-Trade Tariffs as Stocks Move In Tandem",
                "url": "https://finance.yahoo.com/news/t-trade-tariffs-stocks-move-162730960.html"
            },
            {
                "headline": "(Bloomberg) -- Not since the financial crisis has Corporate America been so downbeat about the state of the economy in earnings calls, an ominous sign for investors trying to figure out how much more pain Donald Trump\u2019s trade war will inflict on the stock market.Most Read from BloombergTrump Gives New York \u2018One Last Chance\u2019 to End Congestion FeeDOGE Visits National Gallery of Art to Discuss Museum\u2019s Legal StatusThe Racial Wealth Gap Is Not Just About MoneyThe ratio of positive to negative commen",
                "publication_date": "2025-04-23T00:00:00.000Z",
                "sentiment": "Negative",
                "sentimentScore": "-0.8858",
                "source": "Bloomberg",
                "ticker": "C",
                "title": "CEOs Haven't Been This Gloomy About the US Economy Since the Financial Crisis",
                "url": "https://finance.yahoo.com/news/ceos-havent-gloomy-us-economy-211446199.html"
            },
            {
                "headline": "(Bloomberg) -- Traders have long known Donald Trump intended to use tariffs as a tool for economic policy. Citigroup Inc., a year ago, even offered up a handy framework for trading potential levies on China.Most Read from BloombergTrump Gives New York \u2018One Last Chance\u2019 to End Congestion FeeDOGE Visits National Gallery of Art to Discuss Museum\u2019s Legal StatusThe Racial Wealth Gap Is Not Just About MoneyWhy Car YouTuber Matt Farah Is Fighting for Walkable CitiesBackyard Micro-Flats Aim to Ease Sout",
                "publication_date": "2025-04-23T00:00:00.000Z",
                "sentiment": "Positive",
                "sentimentScore": "0.5719",
                "source": "Bloomberg",
                "ticker": "C",
                "title": "You Can\u2019t\u00a0Out-Trade Tariffs as Stocks Move In Tandem",
                "url": "https://finance.yahoo.com/news/t-trade-tariffs-stocks-move-162730960.html"
            },
            {
                "headline": "(Bloomberg) -- US stocks jumped, wiping out Monday\u2019s plunge, as traders unleashed risky bets that the White House will clinch crucial trade deals with top economic partners. The dollar recovered slightly from Monday\u2019s lows while short-term Treasury yields climbed.Most Read from BloombergTrump Gives New York \u2018One Last Chance\u2019 to End Congestion FeeDOGE Visits National Gallery of Art to Discuss Museum\u2019s Legal StatusThe Racial Wealth Gap Is Not Just About MoneyThe S&P 500 rose 2.5% \u2014 notching its be",
                "publication_date": "2025-04-23T00:00:00.000Z",
                "sentiment": "Positive",
                "sentimentScore": "0.6077",
                "source": "Bloomberg",
                "ticker": "C",
                "title": "US Stocks Rebound as Traders Regain Risk Appetite: Markets Wrap",
                "url": "https://finance.yahoo.com/news/asian-stocks-drop-us-selloff-003202089.html"
            }
        ],
        "avgScore": 0.232675,
        "pctChange": -0.0009026261094014065
    },
    "4 22 2025": {
        "importantArticles": [
            {
                "headline": "Bonds might be down, but they aren't out, according to this expert.",
                "publication_date": "2025-04-22T00:00:00.000Z",
                "sentiment": "Neutral",
                "sentimentScore": "0.0",
                "source": "Yahoo Finance",
                "ticker": "C",
                "title": "Why the bond market may not be in a crisis",
                "url": "https://finance.yahoo.com/news/why-the-bond-market-may-not-be-in-a-crisis-132232215.html"
            },
            {
                "headline": "(Bloomberg) -- The sell-America trade gathered momentum on Monday on concern President Donald Trump will act upon his threat of firing Federal Reserve Chairman Jerome Powell and implement policies that lead to a recession.Most Read from BloombergDOGE Visits National Gallery of Art to Discuss Museum\u2019s Legal StatusTrump Gives New York \u2018One Last Chance\u2019 to End Congestion FeeTrump Administration Takes Over New York Penn Station RevampThe Racial Wealth Gap Is Not Just About MoneyNashville\u2019s $3 Billio",
                "publication_date": "2025-04-22T00:00:00.000Z",
                "sentiment": "Negative",
                "sentimentScore": "-0.2732",
                "source": "Bloomberg",
                "ticker": "C",
                "title": "Trump\u2019s Push Against Powell Adds to Doubts of US\u2019s Haven Status",
                "url": "https://finance.yahoo.com/news/trump-push-against-powell-latest-075114977.html"
            },
            {
                "headline": "(Bloomberg) -- The sell-America trade gathered momentum on Monday on concern President Donald Trump will act upon his threat of firing Federal Reserve Chairman Jerome Powell and implement policies that lead to a recession.Most Read from BloombergDOGE Visits National Gallery of Art to Discuss Museum\u2019s Legal StatusTrump Gives New York \u2018One Last Chance\u2019 to End Congestion FeeTrump Administration Takes Over New York Penn Station RevampThe Racial Wealth Gap Is Not Just About MoneyNashville\u2019s $3 Billio",
                "publication_date": "2025-04-22T00:00:00.000Z",
                "sentiment": "Negative",
                "sentimentScore": "-0.2732",
                "source": "Bloomberg",
                "ticker": "C",
                "title": "Trump\u2019s Push Against Powell Adds to Doubts of US\u2019s Haven Status",
                "url": "https://finance.yahoo.com/news/trump-push-against-powell-latest-075114977.html"
            },
            {
                "headline": "Bonds might be down, but they aren't out, according to this expert.",
                "publication_date": "2025-04-22T00:00:00.000Z",
                "sentiment": "Neutral",
                "sentimentScore": "0.0",
                "source": "Yahoo Finance",
                "ticker": "C",
                "title": "Why the bond market may not be in a crisis",
                "url": "https://finance.yahoo.com/news/why-the-bond-market-may-not-be-in-a-crisis-132232215.html"
            }
        ],
        "avgScore": -0.1366,
        "pctChange": 0.028814880285290882
    },
    "4 21 2025": {
        "importantArticles": [
            {
                "headline": "We recently published a list of the 13 Best American Dividend Stocks to Buy According to Analysts. In this article, we are going to take a look at where Citigroup Inc. (NYSE:C) stands against other best American dividend stocks. Dividend-paying stocks have long benefited investors by delivering consistent and solid returns. During periods of economic uncertainty, [\u2026]",
                "publication_date": "2025-04-21T00:00:00.000Z",
                "sentiment": "Positive",
                "sentimentScore": "0.8225",
                "source": "Insider Monkey",
                "ticker": "C",
                "title": "Citigroup Inc. (C): One of the Best American Dividend Stocks to Buy According to Analysts",
                "url": "https://finance.yahoo.com/news/citigroup-inc-c-one-best-142405233.html"
            },
            {
                "headline": "Citi led by deal value, while Houlihan Lokey topped by deal volume.",
                "publication_date": "2025-04-21T00:00:00.000Z",
                "sentiment": "Positive",
                "sentimentScore": "0.34",
                "source": "Retail Banker International",
                "ticker": "C",
                "title": "Citi and Houlihan Lokey lead Q1 2025 M&A financial advisories",
                "url": "https://finance.yahoo.com/news/citi-houlihan-lokey-lead-q1-132349849.html"
            },
            {
                "headline": "Citi led by deal value, while Houlihan Lokey topped by deal volume.",
                "publication_date": "2025-04-21T00:00:00.000Z",
                "sentiment": "Positive",
                "sentimentScore": "0.34",
                "source": "Retail Banker International",
                "ticker": "C",
                "title": "Citi and Houlihan Lokey lead Q1 2025 M&A financial advisories",
                "url": "https://finance.yahoo.com/news/citi-houlihan-lokey-lead-q1-132349849.html"
            },
            {
                "headline": "We recently published a list of the 13 Best American Dividend Stocks to Buy According to Analysts. In this article, we are going to take a look at where Citigroup Inc. (NYSE:C) stands against other best American dividend stocks. Dividend-paying stocks have long benefited investors by delivering consistent and solid returns. During periods of economic uncertainty, [\u2026]",
                "publication_date": "2025-04-21T00:00:00.000Z",
                "sentiment": "Positive",
                "sentimentScore": "0.8225",
                "source": "Insider Monkey",
                "ticker": "C",
                "title": "Citigroup Inc. (C): One of the Best American Dividend Stocks to Buy According to Analysts",
                "url": "https://finance.yahoo.com/news/citigroup-inc-c-one-best-142405233.html"
            }
        ],
        "avgScore": 0.58125,
        "pctChange": 0.029669875032608088
    },
    "4 17 2025": {
        "importantArticles": [
            {
                "headline": "Citigroup (NYSE: C) is a bank you've likely heard of, given its long history and size.  It is currently offering dividend investors a 3.5% forward dividend yield versus the 2.6% average for banks.  The big problem with Citigroup is what happened during the Great Recession.",
                "publication_date": "2025-04-17T00:00:00.000Z",
                "sentiment": "Negative",
                "sentimentScore": "-0.1027",
                "source": "Motley Fool",
                "ticker": "C",
                "title": "The 3 Biggest Reasons Why This High-Yield Bank Is Better Than Citigroup",
                "url": "https://finance.yahoo.com/news/3-biggest-reasons-why-high-101500038.html"
            },
            {
                "headline": "\u201cI\u2019m not sure any bank finishes its modernization,\u201d CEO Jane Fraser told investors during a Q1 2025 earnings call Tuesday.",
                "publication_date": "2025-04-17T00:00:00.000Z",
                "sentiment": "Negative",
                "sentimentScore": "-0.2411",
                "source": "CIO Dive",
                "ticker": "C",
                "title": "Citi eyes AI productivity gains as it consolidates data systems",
                "url": "https://finance.yahoo.com/news/citi-eyes-ai-productivity-gains-141146916.html"
            },
            {
                "headline": "We recently published a list of 10 Dirt Cheap Stocks To Invest In Now. In this article, we are going to take a look at where Citigroup Inc. (NYSE:C) stands against other dirt cheap stocks to invest in now. Investor\u2019s Guide to Navigating the Volatilitc The stock market has been experiencing volatility and has quickly [\u2026]",
                "publication_date": "2025-04-17T00:00:00.000Z",
                "sentiment": "Negative",
                "sentimentScore": "-0.5859",
                "source": "Insider Monkey",
                "ticker": "C",
                "title": "Is Citigroup Inc. (C) The Dirt Cheap Stock To Invest In Now?",
                "url": "https://finance.yahoo.com/news/citigroup-inc-c-dirt-cheap-212604235.html"
            },
            {
                "headline": "We recently published a list of 10 Dirt Cheap Stocks To Invest In Now. In this article, we are going to take a look at where Citigroup Inc. (NYSE:C) stands against other dirt cheap stocks to invest in now. Investor\u2019s Guide to Navigating the Volatilitc The stock market has been experiencing volatility and has quickly [\u2026]",
                "publication_date": "2025-04-17T00:00:00.000Z",
                "sentiment": "Negative",
                "sentimentScore": "-0.5859",
                "source": "Insider Monkey",
                "ticker": "C",
                "title": "Is Citigroup Inc. (C) The Dirt Cheap Stock To Invest In Now?",
                "url": "https://finance.yahoo.com/news/citigroup-inc-c-dirt-cheap-212604235.html"
            },
            {
                "headline": "\u201cI\u2019m not sure any bank finishes its modernization,\u201d CEO Jane Fraser told investors during a Q1 2025 earnings call Tuesday.",
                "publication_date": "2025-04-17T00:00:00.000Z",
                "sentiment": "Negative",
                "sentimentScore": "-0.2411",
                "source": "CIO Dive",
                "ticker": "C",
                "title": "Citi eyes AI productivity gains as it consolidates data systems",
                "url": "https://finance.yahoo.com/news/citi-eyes-ai-productivity-gains-141146916.html"
            },
            {
                "headline": "Citigroup (NYSE: C) is a bank you've likely heard of, given its long history and size.  It is currently offering dividend investors a 3.5% forward dividend yield versus the 2.6% average for banks.  The big problem with Citigroup is what happened during the Great Recession.",
                "publication_date": "2025-04-17T00:00:00.000Z",
                "sentiment": "Negative",
                "sentimentScore": "-0.1027",
                "source": "Motley Fool",
                "ticker": "C",
                "title": "The 3 Biggest Reasons Why This High-Yield Bank Is Better Than Citigroup",
                "url": "https://finance.yahoo.com/news/3-biggest-reasons-why-high-101500038.html"
            }
        ],
        "avgScore": -0.3099,
        "pctChange": -0.008853776652822382
    },
    "4 16 2025": {
        "importantArticles": [
            {
                "headline": "Says saw \u2018continued momentum\u2019 in each of five businesses. Says securities services gained share. Says Markets had a \u2018good quarter\u2019. Says Equities revenues up 23% y/y. Says M&A revenue nearly doubled. Says USPB was up 2%. Says portfolio continued to perform in line with expectations. Says Transformation investments continue to modernize infrastructure. Says integrating AI directly into business operations. Says \u2018confident in ability to continuing delivering, despite uncertainty of the moment\u2019. Sa",
                "publication_date": "2025-04-16T00:00:00.000Z",
                "sentiment": "Positive",
                "sentimentScore": "0.8532",
                "source": "TipRanks",
                "ticker": "C",
                "title": "Citi says \u2018world is in a wait-and-see mode\u2019",
                "url": "https://finance.yahoo.com/news/citi-says-world-wait-see-151512309.html"
            },
            {
                "headline": "Says \u201clargely complete\u201d on goals of Simplification: Focus on five core interconnected businesses; exit 14 international consumer markets; simplify the organization and management structure; and Culture and Talent: build a winning culture; invest in talent; deliver One Citi (C). Says main priorities for 2025 and 2026 are goals of Transformation: #1 priority; relentless execution; regulatory remediation; modernize infrastructure; data enhancements; and Enhance Business Performance: Maximize unique",
                "publication_date": "2025-04-16T00:00:00.000Z",
                "sentiment": "Positive",
                "sentimentScore": "0.8481",
                "source": "TipRanks",
                "ticker": "C",
                "title": "Citi says \u2018delivering\u2019 on Investor Day priorities",
                "url": "https://finance.yahoo.com/news/citi-says-delivering-investor-day-141532634.html"
            },
            {
                "headline": "Bank of America (BAC) and Citi (C) beat expectations with strong first quarter results, boosting investor confidence and lifting both stocks. RBC Capital Markets bank analyst Gerard Cassidy joins Market Domination to break down what's driving bank earnings. To watch more expert insights and analysis on the latest market action, check out more Market Domination&nbsp;here.",
                "publication_date": "2025-04-16T00:00:00.000Z",
                "sentiment": "Positive",
                "sentimentScore": "0.8316",
                "source": "Yahoo Finance Video",
                "ticker": "C",
                "title": "Big Bank investors 'on edge' despite strong Q1 results",
                "url": "https://finance.yahoo.com/video/big-bank-investors-edge-despite-223109693.html"
            },
            {
                "headline": "(Bloomberg) -- China\u2019s economy showed surprising strength in early 2025 thanks to consumer subsidies and a rush of export shipments to beat tariffs, although an impasse with Donald Trump over the trade war is darkening its outlook and fueling calls for stimulus.Most Read from BloombergHow Did This Suburb Figure Out Mass Transit?Trump Signs Executive Orders on Federal Purchasing, Office SpaceLA County Floats Leaner Budget Burdened by Fire and Legal CostsChina\u2019s gross domestic product grew 5.4% in",
                "publication_date": "2025-04-16T00:00:00.000Z",
                "sentiment": "Negative",
                "sentimentScore": "-0.5267",
                "source": "Bloomberg",
                "ticker": "C",
                "title": "Strong China GDP Growth Fails to Stem Calls for Urgent Stimulus",
                "url": "https://finance.yahoo.com/news/strong-china-gdp-growth-fails-064317061.html"
            },
            {
                "headline": "We recently published a list of Jim Cramer\u2019s Game Plan: 15 Stocks to Watch. In this article, we are going to take a look at where Citigroup Inc. (NYSE:C) stands against other stocks that Jim Cramer discusses. On Friday, Mad Money host Jim Cramer outlined what investors should focus on in the week, especially pointing [\u2026]",
                "publication_date": "2025-04-16T00:00:00.000Z",
                "sentiment": "Negative",
                "sentimentScore": "-0.4939",
                "source": "Insider Monkey",
                "ticker": "C",
                "title": "Citigroup (C) Has Gotten So Loved, It\u2019ll Roar No Matter What \u2013 Jim Cramer Applauds Jane Fraser",
                "url": "https://finance.yahoo.com/news/citigroup-c-gotten-loved-ll-190123580.html"
            },
            {
                "headline": "Stocks closed lower Tuesday, snapping a two-day rally as investor jitters returned to the fore.",
                "publication_date": "2025-04-16T00:00:00.000Z",
                "sentiment": "Negative",
                "sentimentScore": "-0.296",
                "source": "Quartz",
                "ticker": "C",
                "title": "Stocks fizzle after two-day rally driven by bank earnings and tech",
                "url": "https://finance.yahoo.com/news/wall-street-banks-cashing-trade-123249767.html"
            }
        ],
        "avgScore": 0.31210588235294123,
        "pctChange": 0.0185185435448625
    },
    "4 15 2025": {
        "importantArticles": [
            {
                "headline": "Citigroup (NYSE:C) recently reported strong first-quarter earnings, with net income and net interest income both showing marked year-over-year growth. The company's share price reflected this positive performance, rising 7% over the past week. This increase coincided with the broader uplift in the market, which rose 7% as banks and tech stocks led indices higher. While Citigroup's earnings report likely supported the stock's rise, the company also benefited from market trends, with a general...",
                "publication_date": "2025-04-15T00:00:00.000Z",
                "sentiment": "Positive",
                "sentimentScore": "0.9581",
                "source": "Simply Wall St.",
                "ticker": "C",
                "title": "Citigroup (NYSE:C) Sees Q1 2025 Earnings Growth With Net Income Rising To US$4 Billion",
                "url": "https://finance.yahoo.com/news/citigroup-nyse-c-sees-q1-174222735.html"
            },
            {
                "headline": "We recently published a list of the 10 Best Value Dividend Stocks to Buy According to Billionaires. In this article, we are going to take a look at where Citigroup Inc. (NYSE:C) stands against other best value dividend stocks. Dividends, though sometimes underappreciated, have significantly contributed to long-term investor gains. Between 1960 and the end of [\u2026]",
                "publication_date": "2025-04-15T00:00:00.000Z",
                "sentiment": "Positive",
                "sentimentScore": "0.9393",
                "source": "Insider Monkey",
                "ticker": "C",
                "title": "Citigroup Inc. (C): Among the Best Value Dividend Stocks to Buy According to Billionaires?",
                "url": "https://finance.yahoo.com/news/citigroup-inc-c-among-best-113356563.html"
            },
            {
                "headline": "Citi and Bank of America posted first-quarter net interest income of $14 billion and $14.4 billion, respectively.  Wall Street expected $14.49 billion of NII for the quarter at BofA, according to data compiled by FactSet, and $13.56 billion at Citi.  BofA said in January that it expected to drive between $14.5 billion and $14.6 billion of net interest income on a fully taxable equivalent basis for the first quarter.",
                "publication_date": "2025-04-15T00:00:00.000Z",
                "sentiment": "Positive",
                "sentimentScore": "0.8126",
                "source": "Barrons.com",
                "ticker": "C",
                "title": "Bank of America and Citi Report Higher NII, Reiterate Outlook",
                "url": "https://finance.yahoo.com/m/fdf73818-b495-3cef-9a72-be51a13cb81c/bank-of-america-and-citi.html"
            },
            {
                "headline": "(Bloomberg) -- As China staggers into a slowdown caused by Donald Trump\u2019s trade war, a hobbled jobs market is impairing the resilience Beijing needs to battle it out against the US.Most Read from BloombergHow Did This Suburb Figure Out Mass Transit?The Secret Formula for Faster TrainsEven Oslo Has an Air Quality ProblemNYC Tourist Helicopter Crashes in Hudson River, Killing SixLisbon Mayor Wants Companies to Help Fix City\u2019s Housing ShortageTrump\u2019s 145% tariffs on China\u2019s goods are threatening to",
                "publication_date": "2025-04-15T00:00:00.000Z",
                "sentiment": "Negative",
                "sentimentScore": "-0.9118",
                "source": "Bloomberg",
                "ticker": "C",
                "title": "Tariffs to Impact Millions of Chinese Workers in Blow to Economy",
                "url": "https://finance.yahoo.com/news/tariffs-impact-millions-chinese-workers-060000128.html"
            },
            {
                "headline": "There is a lot for traders to watch on Tuesday, April 15. Stock futures (ES=F, NQ=F, YM=F) are mixed as the latest Bank of America fund manager survey shows investors are turning bearish. Boeing (BA) is the latest target in the trade war between the US and China, according to a report from Bloomberg. Both Bank of America (BAC) and Citigroup (C) posted better-than-expected earnings. To watch more expert insights and analysis on the latest market action, check out more Morning Brief here.",
                "publication_date": "2025-04-15T00:00:00.000Z",
                "sentiment": "Negative",
                "sentimentScore": "-0.5994",
                "source": "Yahoo Finance Video",
                "ticker": "C",
                "title": "Futures waver, China halts Boeing deliveries, bank earnings: 3 Things",
                "url": "https://finance.yahoo.com/video/futures-waver-china-halts-boeing-131220346.html"
            },
            {
                "headline": "(Bloomberg) -- Supply Lines is a daily newsletter that tracks global trade. Sign up here.Most Read from BloombergHow Did This Suburb Figure Out Mass Transit?Even Oslo Has an Air Quality ProblemLA County Floats Leaner Budget Burdened by Fire and Legal Costs$15 Million Fund Bets Leadership Training Can Improve Chicago PolicingTrump Signs Executive Orders on Federal Purchasing, Office SpaceMajor players in the US copper industry have called on President Donald Trump to restrict exports of ore and s",
                "publication_date": "2025-04-15T00:00:00.000Z",
                "sentiment": "Negative",
                "sentimentScore": "-0.5106",
                "source": "Bloomberg",
                "ticker": "C",
                "title": "US Copper Industry Seeks Export Curbs Instead of Tariffs",
                "url": "https://finance.yahoo.com/news/us-copper-industry-seeks-export-110350871.html"
            }
        ],
        "avgScore": 0.2603903225806452,
        "pctChange": -0.03466505974599679
    },
    "4 14 2025": {
        "importantArticles": [
            {
                "headline": "(Bloomberg) -- A knee-jerk reaction to President Donald Trump\u2019s 90-day pause on broad tariffs propelled US stocks to one of their best days on record last week. Ironically, that could be a harbinger of tough times for equity investors.Most Read from BloombergThe Secret Formula for Faster TrainsNYC Tourist Helicopter Crashes in Hudson River, Killing SixEven Oslo Has an Air Quality ProblemInside the Quiet, Extravagant Expansion of the Frick CollectionLisbon Mayor Wants Companies to Help Fix City\u2019s",
                "publication_date": "2025-04-14T00:00:00.000Z",
                "sentiment": "Positive",
                "sentimentScore": "0.25",
                "source": "Bloomberg",
                "ticker": "C",
                "title": "Stock market\u2019s extreme moves portend lasting trouble for traders",
                "url": "https://finance.yahoo.com/news/stock-market-extreme-moves-portend-093000798.html"
            },
            {
                "headline": "Does JPM stock deserve a place in your investment portfolio after posting an upbeat Q1 performance? Let's find out.",
                "publication_date": "2025-04-14T00:00:00.000Z",
                "sentiment": "Neutral",
                "sentimentScore": "0.0",
                "source": "Zacks",
                "ticker": "C",
                "title": "How to Play JPMorgan Stock After Upbeat Q1 Earnings Performance",
                "url": "https://finance.yahoo.com/news/play-jpmorgan-stock-upbeat-q1-131300969.html"
            },
            {
                "headline": "(Bloomberg) -- Morgan Stanley and Citigroup Inc. slashed their estimates for 2025 earnings as companies kick off their first-quarter reports, joining a wave of Wall Street banks warning that tariffs will curb profit growth. Most Read from BloombergThe Secret Formula for Faster TrainsNYC Tourist Helicopter Crashes in Hudson River, Killing SixEven Oslo Has an Air Quality ProblemInside the Quiet, Extravagant Expansion of the Frick CollectionLisbon Mayor Wants Companies to Help Fix City\u2019s Housing Sh",
                "publication_date": "2025-04-14T00:00:00.000Z",
                "sentiment": "Negative",
                "sentimentScore": "-0.128",
                "source": "Bloomberg",
                "ticker": "C",
                "title": "Morgan Stanley, Citi cut US earnings estimates as season starts",
                "url": "https://finance.yahoo.com/news/morgan-stanley-citi-cut-us-085941613.html"
            },
            {
                "headline": "Goldman Sachs Group Inc.'s stock traders posted their highest quarterly revenue haul on record, riding a wave of volatility triggered by an emerging global trade war that's roiled financial markets. KBW Analyst of Large Cap Banks David Konrad has more on the story.",
                "publication_date": "2025-04-14T00:00:00.000Z",
                "sentiment": "Negative",
                "sentimentScore": "-0.5994",
                "source": "Bloomberg",
                "ticker": "C",
                "title": "KBW Analyst on Goldman Sachs' Record Quarter",
                "url": "https://finance.yahoo.com/video/kbw-analyst-goldman-sachs-record-180342835.html"
            },
            {
                "headline": "(Bloomberg) -- Morgan Stanley and Citigroup Inc. slashed their estimates for 2025 earnings as companies kick off their first-quarter reports, joining a wave of Wall Street banks warning that tariffs will curb profit growth. Most Read from BloombergThe Secret Formula for Faster TrainsNYC Tourist Helicopter Crashes in Hudson River, Killing SixEven Oslo Has an Air Quality ProblemInside the Quiet, Extravagant Expansion of the Frick CollectionLisbon Mayor Wants Companies to Help Fix City\u2019s Housing Sh",
                "publication_date": "2025-04-14T00:00:00.000Z",
                "sentiment": "Negative",
                "sentimentScore": "-0.128",
                "source": "Bloomberg",
                "ticker": "C",
                "title": "Morgan Stanley, Citi cut US earnings estimates as season starts",
                "url": "https://finance.yahoo.com/news/morgan-stanley-citi-cut-us-085941613.html"
            },
            {
                "headline": "Does JPM stock deserve a place in your investment portfolio after posting an upbeat Q1 performance? Let's find out.",
                "publication_date": "2025-04-14T00:00:00.000Z",
                "sentiment": "Neutral",
                "sentimentScore": "0.0",
                "source": "Zacks",
                "ticker": "C",
                "title": "How to Play JPMorgan Stock After Upbeat Q1 Earnings Performance",
                "url": "https://finance.yahoo.com/news/play-jpmorgan-stock-upbeat-q1-131300969.html"
            }
        ],
        "avgScore": -0.11935000000000001,
        "pctChange": 0.01755774420940793
    },
    "4 11 2025": {
        "importantArticles": [
            {
                "headline": "Earnings mean less, and old outlooks mean nothing when tariff policy is all Wall Street cares about.",
                "publication_date": "2025-04-11T00:00:00.000Z",
                "sentiment": "Positive",
                "sentimentScore": "0.4588",
                "source": "Yahoo Finance",
                "ticker": "C",
                "title": "Tariff uncertainty muddies \u2014 and refocuses \u2014 earnings season: Morning Brief",
                "url": "https://finance.yahoo.com/news/tariff-uncertainty-muddies--and-refocuses--earnings-season-morning-brief-100025876.html"
            },
            {
                "headline": "Earnings preview of key companies reporting this week and what to look out for.",
                "publication_date": "2025-04-11T00:00:00.000Z",
                "sentiment": "Neutral",
                "sentimentScore": "0.0",
                "source": "Yahoo Finance UK",
                "ticker": "C",
                "title": "Stocks to watch this week: Goldman Sachs, TSMC, ASML, Netflix, LVMH and Sainsbury's",
                "url": "https://finance.yahoo.com/news/goldman-sachs-tsmc-asml-netflix-lvmh-and-sainsburys-stocks-to-watch-131111514.html"
            },
            {
                "headline": "MOSCOW (Reuters) -Brokerage customers of the Russian subsidiary of U.S. bank Citi have started receiving coupon payments on securities frozen in Europe by Western sanctions, according to Russian law firms, citing their clients.  Citi did not immediately respond to a request for comment.  Western sanctions imposed in June 2022 on Russia's National Settlement Depository (NSD) in response to Russia's military offensive in Ukraine led to Russian investors' holdings in European depositories Euroclear and Clearstream being frozen.",
                "publication_date": "2025-04-11T00:00:00.000Z",
                "sentiment": "Negative",
                "sentimentScore": "-0.2732",
                "source": "Reuters",
                "ticker": "C",
                "title": "Citi clients in Russia receiving some frozen funds, Russian lawyers say",
                "url": "https://finance.yahoo.com/news/citi-clients-russia-receiving-frozen-085141197.html"
            },
            {
                "headline": "(Bloomberg) -- After a week of wild swings in the US bond market, China\u2019s holdings of Treasuries are increasingly under scrutiny from analysts around the world.Most Read from BloombergMidtown Office Building Evacuated on Concerns of Wall CollapseThe Secret Formula for Faster TrainsIn Chicago, a Former Steel Mill Looks to Make a Quantum LeapNYC Tourist Helicopter Crashes in Hudson River, Killing SixInside the Quiet, Extravagant Expansion of the Frick CollectionSome have gone as far as suggesting",
                "publication_date": "2025-04-11T00:00:00.000Z",
                "sentiment": "Negative",
                "sentimentScore": "-0.5423",
                "source": "Bloomberg",
                "ticker": "C",
                "title": "Bond Analysts Debate If China Had Role in Treasuries Swings",
                "url": "https://finance.yahoo.com/news/bond-analysts-debate-china-had-073146113.html"
            },
            {
                "headline": "MOSCOW (Reuters) -Brokerage customers of the Russian subsidiary of U.S. bank Citi have started receiving coupon payments on securities frozen in Europe by Western sanctions, according to Russian law firms, citing their clients.  Citi did not immediately respond to a request for comment.  Western sanctions imposed in June 2022 on Russia's National Settlement Depository (NSD) in response to Russia's military offensive in Ukraine led to Russian investors' holdings in European depositories Euroclear and Clearstream being frozen.",
                "publication_date": "2025-04-11T00:00:00.000Z",
                "sentiment": "Negative",
                "sentimentScore": "-0.2732",
                "source": "Reuters",
                "ticker": "C",
                "title": "Citi clients in Russia receiving some frozen funds, Russian lawyers say",
                "url": "https://finance.yahoo.com/news/citi-clients-russia-receiving-frozen-085141197.html"
            },
            {
                "headline": "Earnings preview of key companies reporting this week and what to look out for.",
                "publication_date": "2025-04-11T00:00:00.000Z",
                "sentiment": "Neutral",
                "sentimentScore": "0.0",
                "source": "Yahoo Finance UK",
                "ticker": "C",
                "title": "Stocks to watch this week: Goldman Sachs, TSMC, ASML, Netflix, LVMH and Sainsbury's",
                "url": "https://finance.yahoo.com/news/goldman-sachs-tsmc-asml-netflix-lvmh-and-sainsburys-stocks-to-watch-131111514.html"
            }
        ],
        "avgScore": -0.089175,
        "pctChange": 0.025632735994478715
    },
    "4 10 2025": {
        "importantArticles": [
            {
                "headline": "Beyond analysts' top -and-bottom-line estimates for Citigroup (C), evaluate projections for some of its key metrics to gain a better insight into how the business might have performed for the quarter ended March 2025.",
                "publication_date": "2025-04-10T00:00:00.000Z",
                "sentiment": "Positive",
                "sentimentScore": "0.7964",
                "source": "Zacks",
                "ticker": "C",
                "title": "What Analyst Projections for Key Metrics Reveal About Citigroup (C) Q1 Earnings",
                "url": "https://finance.yahoo.com/news/analyst-projections-key-metrics-reveal-131511814.html"
            },
            {
                "headline": "Raymond Gatcliffe has been appointed Country Officer and Chief Executive Officer for Citibank Canada, effective April 1, 2025. He succeeds John Hastings who will stay on as a member of the Citibank Canada Board of Directors.",
                "publication_date": "2025-04-10T00:00:00.000Z",
                "sentiment": "Positive",
                "sentimentScore": "0.743",
                "source": "CNW Group",
                "ticker": "C",
                "title": "Raymond Gatcliffe appointed Country Officer and Chief Executive Officer for Citibank Canada",
                "url": "https://finance.yahoo.com/news/raymond-gatcliffe-appointed-country-officer-151500843.html"
            },
            {
                "headline": "Gatcliffe, whose appointment is effective April 1, succeeds CEO John Hastings, who will stay on as a member of the board.  The leadership change comes amid a shake up of the decades-old global trade order triggered by sweeping tariffs from U.S. President Donald Trump.  Canadian Prime Minister Mark Carney on Thursday reiterated that Ottawa would respond with force until Washington lifted the tariffs.",
                "publication_date": "2025-04-10T00:00:00.000Z",
                "sentiment": "Positive",
                "sentimentScore": "0.6808",
                "source": "Reuters",
                "ticker": "C",
                "title": "Citi names insider Raymond Gatcliffe as CEO of Canada operations",
                "url": "https://finance.yahoo.com/news/citi-names-insider-raymond-gatcliffe-170244550.html"
            },
            {
                "headline": "(Bloomberg) -- Supply Lines is a daily newsletter that tracks global trade. Sign up here.US President Donald Trump may have announced a delay in some of his tariff plans, but the first signs of an economically-damaging slowdown in global trade are already emerging as companies around the world hit their own pause button on orders and he continues to escalate his trade war with China. Trump announced Wednesday that he would increase import duties on Chinese goods to 125% while also announcing a 9",
                "publication_date": "2025-04-10T00:00:00.000Z",
                "sentiment": "Negative",
                "sentimentScore": "-0.6187",
                "source": "Bloomberg",
                "ticker": "C",
                "title": "Trump is already slowing global trade as companies pause orders",
                "url": "https://finance.yahoo.com/news/trump-already-slowing-global-trade-090000989.html"
            },
            {
                "headline": "C's first-quarter 2025 results will likely reflect the benefits of a rise in NII and loan demand. Yet, rising costs are likely to have hurt.",
                "publication_date": "2025-04-10T00:00:00.000Z",
                "sentiment": "Negative",
                "sentimentScore": "-0.3182",
                "source": "Zacks",
                "ticker": "C",
                "title": "Is Citigroup Worth a Spot in Your Portfolio Ahead of Q1 Earnings?",
                "url": "https://finance.yahoo.com/news/citigroup-worth-spot-portfolio-ahead-160400165.html"
            },
            {
                "headline": "Citigroup (C) witnessed a jump in share price last session on above-average trading volume. The latest trend in earnings estimate revisions for the stock doesn't suggest further strength down the road.",
                "publication_date": "2025-04-10T00:00:00.000Z",
                "sentiment": "Negative",
                "sentimentScore": "-0.1098",
                "source": "Zacks",
                "ticker": "C",
                "title": "Citigroup (C) Soars 9.2%: Is Further Upside Left in the Stock?",
                "url": "https://finance.yahoo.com/news/citigroup-c-soars-9-2-123000509.html"
            }
        ],
        "avgScore": 0.25770000000000004,
        "pctChange": 0.0008118077112627837
    },
    "4 9 2025": {
        "importantArticles": [
            {
                "headline": "Both C and WFC's progress with strategic initiatives to unlock growth looks encouraging. Read on to know which is a better investment option now.",
                "publication_date": "2025-04-09T00:00:00.000Z",
                "sentiment": "Positive",
                "sentimentScore": "0.8934",
                "source": "Zacks",
                "ticker": "C",
                "title": "Citigroup Vs Wells Fargo: Which Bank Stock is a Smarter Investment?",
                "url": "https://finance.yahoo.com/news/citigroup-vs-wells-fargo-bank-163600282.html"
            },
            {
                "headline": "Citigroup Chief Technology Officer David Griffiths has expanded the rollout of new generative AI productivity tools.",
                "publication_date": "2025-04-09T00:00:00.000Z",
                "sentiment": "Neutral",
                "sentimentScore": "0.0",
                "source": "Fortune",
                "ticker": "C",
                "title": "How Citi\u2019s CTO is rolling out new gen AI productivity tools to more employees across the globe",
                "url": "https://finance.yahoo.com/news/citi-cto-rolling-gen-ai-151815264.html"
            },
            {
                "headline": "Citigroup (C) closed at $58.71 in the latest trading session, marking a -0.24% move from the prior day.",
                "publication_date": "2025-04-09T00:00:00.000Z",
                "sentiment": "Neutral",
                "sentimentScore": "0.0",
                "source": "Zacks",
                "ticker": "C",
                "title": "Citigroup (C) Stock Moves -0.24%: What You Should Know",
                "url": "https://finance.yahoo.com/news/citigroup-c-stock-moves-0-215016171.html"
            },
            {
                "headline": "Josh Lipton goes over some of the top trending stories on this segment of Market Minute. Apple (AAPL) stock rebounds after previous losses, though shares are down over 20% over the past five days. Oil futures (CL=F) are sliding due to the escalating trade war as China announced retaliatory tariffs of 84% on US goods, effective April 10th. Bank stocks, including JPMorgan (JPM), Wells Fargo (WFC), and Citigroup (C) are under pressure after JPMorgan Chase CEO Jamie Dimon warned that a US recession is likely. Stay up to date on the latest market action, minute-by-minute, with Yahoo Finance's Market Minute.",
                "publication_date": "2025-04-09T00:00:00.000Z",
                "sentiment": "Negative",
                "sentimentScore": "-0.6808",
                "source": "Yahoo Finance Video",
                "ticker": "C",
                "title": "Apple, oil futures, bank stocks: Market Minute",
                "url": "https://finance.yahoo.com/video/apple-oil-futures-bank-stocks-171938467.html"
            },
            {
                "headline": "(Bloomberg) -- The angry mutterings at the Permian Basin Petroleum Association\u2019s \u201cSpring Swing\u201d golf tournament this week weren\u2019t all about missed putts or lost balls. The Texas oilmen on the fairways had a more serious concern: The president they helped elect was tanking oil prices.The market rout sparked by President Donald Trump\u2019s trade war is touching almost every part of the economy. But there are probably few industries feeling more aggrieved right now than US shale oil. Over the last 15 y",
                "publication_date": "2025-04-09T00:00:00.000Z",
                "sentiment": "Negative",
                "sentimentScore": "-0.6593",
                "source": "Bloomberg",
                "ticker": "C",
                "title": "Texas Oil Executives Are Frustrated at Trump for Crushing Crude Prices",
                "url": "https://finance.yahoo.com/news/texas-wildcatters-impatient-trump-oil-140741365.html"
            },
            {
                "headline": "Citigroup (C) closed at $58.71 in the latest trading session, marking a -0.24% move from the prior day.",
                "publication_date": "2025-04-09T00:00:00.000Z",
                "sentiment": "Neutral",
                "sentimentScore": "0.0",
                "source": "Zacks",
                "ticker": "C",
                "title": "Citigroup (C) Stock Moves -0.24%: What You Should Know",
                "url": "https://finance.yahoo.com/news/citigroup-c-stock-moves-0-215016171.html"
            }
        ],
        "avgScore": -0.08934,
        "pctChange": -0.03990648967106072
    },
    "4 8 2025": {
        "importantArticles": [
            {
                "headline": "President Donald Trump's sweeping tariffs have sent the market into free fall and it's clear investors are starting to panic as they think about the adverse effects of a transitioning economy, slower growth, and a potential recession or even stagflation.  As scary as times like this can seem, however, they have also presented the best buying opportunities for calm investors who have long investing horizons ahead of them.  While investors have been sprinting to the sidelines, Nygren told CNBC last week that he swooped in and bought three beaten-down stocks that already have negative expectations baked in.",
                "publication_date": "2025-04-08T00:00:00.000Z",
                "sentiment": "Positive",
                "sentimentScore": "0.5574",
                "source": "Motley Fool",
                "ticker": "C",
                "title": "While Trump's Tariffs Sent Investors Sprinting to the Sidelines, Oakmark's Bill Nygren Swooped in and Bought These 3 Beaten-Down Stocks",
                "url": "https://finance.yahoo.com/news/while-trumps-tariffs-sent-investors-090000676.html"
            },
            {
                "headline": "Citigroup (C) doesn't possess the right combination of the two key ingredients for a likely earnings beat in its upcoming report. Get prepared with the key expectations.",
                "publication_date": "2025-04-08T00:00:00.000Z",
                "sentiment": "Positive",
                "sentimentScore": "0.2263",
                "source": "Zacks",
                "ticker": "C",
                "title": "Citigroup (C) Reports Next Week: Wall Street Expects Earnings Growth",
                "url": "https://finance.yahoo.com/news/citigroup-c-reports-next-week-140008306.html"
            },
            {
                "headline": "The sector is among the least defensive groups in the stock market, given lenders\u2019 exposure to the economy and financial markets.",
                "publication_date": "2025-04-08T00:00:00.000Z",
                "sentiment": "Neutral",
                "sentimentScore": "-0.0191",
                "source": "Barrons.com",
                "ticker": "C",
                "title": "Goldman Sachs and 3 More Banks That Look Cheap After Selloff",
                "url": "https://finance.yahoo.com/m/2e74a268-90c5-3e42-9373-c57c173cd1dc/goldman-sachs-and-3-more.html"
            },
            {
                "headline": "The sector is among the least defensive groups in the stock market, given lenders\u2019 exposure to the economy and financial markets.",
                "publication_date": "2025-04-08T00:00:00.000Z",
                "sentiment": "Neutral",
                "sentimentScore": "-0.0191",
                "source": "Barrons.com",
                "ticker": "C",
                "title": "Goldman Sachs and 3 More Banks That Look Cheap After Selloff",
                "url": "https://finance.yahoo.com/m/2e74a268-90c5-3e42-9373-c57c173cd1dc/goldman-sachs-and-3-more.html"
            },
            {
                "headline": "Citigroup (C) doesn't possess the right combination of the two key ingredients for a likely earnings beat in its upcoming report. Get prepared with the key expectations.",
                "publication_date": "2025-04-08T00:00:00.000Z",
                "sentiment": "Positive",
                "sentimentScore": "0.2263",
                "source": "Zacks",
                "ticker": "C",
                "title": "Citigroup (C) Reports Next Week: Wall Street Expects Earnings Growth",
                "url": "https://finance.yahoo.com/news/citigroup-c-reports-next-week-140008306.html"
            },
            {
                "headline": "President Donald Trump's sweeping tariffs have sent the market into free fall and it's clear investors are starting to panic as they think about the adverse effects of a transitioning economy, slower growth, and a potential recession or even stagflation.  As scary as times like this can seem, however, they have also presented the best buying opportunities for calm investors who have long investing horizons ahead of them.  While investors have been sprinting to the sidelines, Nygren told CNBC last week that he swooped in and bought three beaten-down stocks that already have negative expectations baked in.",
                "publication_date": "2025-04-08T00:00:00.000Z",
                "sentiment": "Positive",
                "sentimentScore": "0.5574",
                "source": "Motley Fool",
                "ticker": "C",
                "title": "While Trump's Tariffs Sent Investors Sprinting to the Sidelines, Oakmark's Bill Nygren Swooped in and Bought These 3 Beaten-Down Stocks",
                "url": "https://finance.yahoo.com/news/while-trumps-tariffs-sent-investors-090000676.html"
            }
        ],
        "avgScore": 0.2548666666666667,
        "pctChange": 0.09154332186847076
    },
    "4 7 2025": {
        "importantArticles": [
            {
                "headline": "We recently published a list of Starter Stock Portfolio 12 Safe Stocks to Buy. In this article, we are going to take a look at where Citigroup Inc. (NYSE:C) stands against other best beginner stocks. The US stock market has experienced a turbulent first quarter of 2025, marked by increased volatility and negative returns across [\u2026]",
                "publication_date": "2025-04-07T00:00:00.000Z",
                "sentiment": "Positive",
                "sentimentScore": "0.6705",
                "source": "Insider Monkey",
                "ticker": "C",
                "title": "Citigroup Inc. (C): Among the Best Beginner Stocks",
                "url": "https://finance.yahoo.com/news/citigroup-inc-c-among-best-205526842.html"
            },
            {
                "headline": "Glass Lewis changed its recommendation on Citi after the bank issued an updated disclosure explaining $52.25 million in pay to its head of banking, Vis Raghavan.",
                "publication_date": "2025-04-07T00:00:00.000Z",
                "sentiment": "Negative",
                "sentimentScore": "-0.1027",
                "source": "Banking Dive",
                "ticker": "C",
                "title": "Citi, BofA pay packages spur pushback from proxy advisers",
                "url": "https://finance.yahoo.com/news/citi-bofa-pay-packages-spur-121615553.html"
            },
            {
                "headline": "(Bloomberg) -- China warned against panic in the face of Donald Trump\u2019s tariff hikes, saying it has plenty of policy room to defend the economy but without ruling out negotiations with the US.Most Read from BloombergHousing Agency Aims to Relocate Its DC HeadquartersBoston Mayor Wu Embraces Trump Resistance as Campaign Heats UpThis Skinny Mexico City Tower Is Just 14 Feet Wide on One SideThe Irish Hot Press Is the Low-Tech Laundry Trick the World NeedsWhat Would \u2018Transportation Abundance\u2019 Look L",
                "publication_date": "2025-04-07T00:00:00.000Z",
                "sentiment": "Negative",
                "sentimentScore": "-0.4588",
                "source": "Bloomberg",
                "ticker": "C",
                "title": "China Appeals for Calm, Readies Plans to Counter Trump\u2019s Tariffs",
                "url": "https://finance.yahoo.com/news/china-floats-rate-cuts-industry-223137239.html"
            },
            {
                "headline": "(Bloomberg) -- Two weeks ago, copper prices were surging as traders warned that threatened US tariffs on the metal would squeeze global supplies. Now, bulls are confronting one of the market\u2019s worst-ever selloffs as President Donald Trump\u2019s broader trade war upends the outlook for demand.Most Read from BloombergHousing Agency Aims to Relocate Its DC HeadquartersBoston Mayor Wu Embraces Trump Resistance as Campaign Heats UpThis Skinny Mexico City Tower Is Just 14 Feet Wide on One SideThe Irish Ho",
                "publication_date": "2025-04-07T00:00:00.000Z",
                "sentiment": "Negative",
                "sentimentScore": "-0.8625",
                "source": "Bloomberg",
                "ticker": "C",
                "title": "Copper\u2019s Bull Run Turns to Rout as Reality of Tariffs Bites",
                "url": "https://finance.yahoo.com/news/copper-bull-run-turns-rout-213131301.html"
            },
            {
                "headline": "(Bloomberg) -- China warned against panic in the face of Donald Trump\u2019s tariff hikes, saying it has plenty of policy room to defend the economy but without ruling out negotiations with the US.Most Read from BloombergHousing Agency Aims to Relocate Its DC HeadquartersBoston Mayor Wu Embraces Trump Resistance as Campaign Heats UpThis Skinny Mexico City Tower Is Just 14 Feet Wide on One SideThe Irish Hot Press Is the Low-Tech Laundry Trick the World NeedsWhat Would \u2018Transportation Abundance\u2019 Look L",
                "publication_date": "2025-04-07T00:00:00.000Z",
                "sentiment": "Negative",
                "sentimentScore": "-0.4588",
                "source": "Bloomberg",
                "ticker": "C",
                "title": "China Appeals for Calm, Readies Plans to Counter Trump\u2019s Tariffs",
                "url": "https://finance.yahoo.com/news/china-floats-rate-cuts-industry-223137239.html"
            },
            {
                "headline": "Glass Lewis changed its recommendation on Citi after the bank issued an updated disclosure explaining $52.25 million in pay to its head of banking, Vis Raghavan.",
                "publication_date": "2025-04-07T00:00:00.000Z",
                "sentiment": "Negative",
                "sentimentScore": "-0.1027",
                "source": "Banking Dive",
                "ticker": "C",
                "title": "Citi, BofA pay packages spur pushback from proxy advisers",
                "url": "https://finance.yahoo.com/news/citi-bofa-pay-packages-spur-121615553.html"
            }
        ],
        "avgScore": -0.18837500000000001,
        "pctChange": -0.001359354603766056
    },
    "4 4 2025": {
        "importantArticles": [
            {
                "headline": "Banks are set to kick off first quarter earnings season next week. Bloomberg Intelligence director of research global strategy team Alison Williams joins Catalyst with host Madison Mills to discuss what investors can expect from bank earnings. To watch more expert insights and analysis on the latest market action, check out more Catalysts here.",
                "publication_date": "2025-04-04T00:00:00.000Z",
                "sentiment": "Positive",
                "sentimentScore": "0.4767",
                "source": "Yahoo Finance Video",
                "ticker": "C",
                "title": "Banks to kick off earnings: 'Credit risk' will become key concern",
                "url": "https://finance.yahoo.com/video/banks-kick-off-earnings-credit-152314153.html"
            },
            {
                "headline": "The latest investor updates on stocks that are trending on Friday",
                "publication_date": "2025-04-04T00:00:00.000Z",
                "sentiment": "Neutral",
                "sentimentScore": "0.0",
                "source": "Yahoo Finance UK",
                "ticker": "C",
                "title": "Trending tickers: Apple, Nike, Starbucks, Best Buy and Restoration Hardware",
                "url": "https://finance.yahoo.com/news/apple-nike-starbucks-best-buy-restoration-hardware-trending-tickers-091237531.html"
            },
            {
                "headline": "NEW YORK, April 03, 2025--Citigroup Inc. is announcing the redemption, in whole, constituting $3,500,000,000 of its 3.106% Fixed Rate / Floating Rate Notes due 2026 (the \"notes\") (ISIN: US172967MQ12).",
                "publication_date": "2025-04-04T00:00:00.000Z",
                "sentiment": "Neutral",
                "sentimentScore": "0.0",
                "source": "Business Wire",
                "ticker": "C",
                "title": "Citigroup Announces $3.5 Billion Redemption of 3.106% Fixed Rate/Floating Rate Notes Due 2026",
                "url": "https://finance.yahoo.com/news/citigroup-announces-3-5-billion-201500099.html"
            },
            {
                "headline": "(Bloomberg) -- Roughly $2.5 trillion was erased from the S&P 500 Index on Thursday amid worries that President Donald Trump\u2019s sweeping new round of tariffs could plunge the economy into a recession.Most Read from BloombergHousing Agency Aims to Relocate Its DC HeadquartersMetro-North Is Faster Than Acela on NYC-New Haven Route After Signal UpdatesLocal Governments Vie for Fired Federal WorkersLondon Clears Final Hurdle for More High-Speed Trains to EuropeWhat Would \u2018Transportation Abundance\u2019 Loo",
                "publication_date": "2025-04-04T00:00:00.000Z",
                "sentiment": "Negative",
                "sentimentScore": "-0.7269",
                "source": "Bloomberg",
                "ticker": "C",
                "title": "Trump Tariffs Wipe Out $2.5 Trillion From US Stock Market",
                "url": "https://finance.yahoo.com/news/trump-tariffs-set-wipe-nearly-120038363.html"
            },
            {
                "headline": "Stocks of the biggest banks and private-equity firms plunged Thursday as concerns mounted about how Wall Street giants and their customers might be affected by heightened odds of a US recession.",
                "publication_date": "2025-04-04T00:00:00.000Z",
                "sentiment": "Negative",
                "sentimentScore": "-0.5267",
                "source": "Yahoo Finance",
                "ticker": "C",
                "title": "Stocks of Wall Street giants plunge as Trump tariff turmoil roils the finance world",
                "url": "https://finance.yahoo.com/news/stocks-of-wall-street-giants-plunge-as-trump-tariff-turmoil-roils-the-finance-world-190455146.html"
            },
            {
                "headline": "Citigroup (NYSE:C) recently announced dividend declarations, with a common stock dividend of $0.56 per share, amidst a challenging market backdrop where major indexes, including the Dow, are experiencing significant tumbles due to escalating trade tensions. As the global trade landscape remains uncertain, Citigroup's stock price moved downward by 11.20% over the last quarter. The market's overall decline of 5.6% during this time reflects broader economic unease, amplified by tariff...",
                "publication_date": "2025-04-04T00:00:00.000Z",
                "sentiment": "Negative",
                "sentimentScore": "-0.4588",
                "source": "Simply Wall St.",
                "ticker": "C",
                "title": "Citigroup (NYSE:C) Declares US$0.56 Dividend Despite 12% Share Price Dip",
                "url": "https://finance.yahoo.com/news/citigroup-nyse-c-declares-us-181337272.html"
            }
        ],
        "avgScore": -0.20595,
        "pctChange": 0.01238598645752965
    },
    "4 3 2025": {
        "importantArticles": [
            {
                "headline": "The lawsuit accused the New York City-based bank of \u201cunabashed racial discrimination\u201d for waiving ATM fees for customers of minority-owned banks but not for white-owned banks.",
                "publication_date": "2025-04-03T00:00:00.000Z",
                "sentiment": "Negative",
                "sentimentScore": "-0.2617",
                "source": "Banking Dive",
                "ticker": "C",
                "title": "Judge tosses racial bias suit against Citi over ATM fee waivers",
                "url": "https://finance.yahoo.com/news/judge-tosses-racial-bias-suit-113115383.html"
            },
            {
                "headline": "Investing.com -- Citi has made a series of rating adjustments across U.S. retail stocks, reacting to a shifting macro backdrop marked by higher tariffs and rising recession risks.",
                "publication_date": "2025-04-03T00:00:00.000Z",
                "sentiment": "Negative",
                "sentimentScore": "-0.5994",
                "source": "Investing.com",
                "ticker": "C",
                "title": "Citi reshuffles U.S. retail stock ratings after reciprocal tariff announcement",
                "url": "https://finance.yahoo.com/news/citi-reshuffles-u-retail-stock-125540144.html"
            },
            {
                "headline": "(Bloomberg) -- The yield on benchmark Treasuries fell briefly below 4% for the first time since October as Wall Street fretted that the US economy will end up worse off from President Donald Trump\u2019s trade war.Most Read from BloombergMetro-North Is Faster Than Acela on NYC-New Haven Route After Signal UpdatesHousing Agency Aims to Relocate Its DC HeadquartersLocal Governments Vie for Fired Federal WorkersLondon Clears Final Hurdle for More High-Speed Trains to EuropeWhat Would \u2018Transportation Abu",
                "publication_date": "2025-04-03T00:00:00.000Z",
                "sentiment": "Negative",
                "sentimentScore": "-0.6705",
                "source": "Bloomberg",
                "ticker": "C",
                "title": "US 10-Year Yield Drops Below 4% for First Time Since Trump Won",
                "url": "https://finance.yahoo.com/news/us-10-yield-drops-below-140544183.html"
            },
            {
                "headline": "(Bloomberg) -- A Bloomberg gauge of the dollar dropped the most on record as fears grew that President Donald Trump\u2019s sweeping trade tariffs would batter the US economy.Most Read from BloombergMetro-North Is Faster Than Acela on NYC-New Haven Route After Signal UpdatesLocal Governments Vie for Fired Federal WorkersLondon Clears Final Hurdle for More High-Speed Trains to EuropeHousing Agency Aims to Relocate Its DC HeadquartersWhat Would \u2018Transportation Abundance\u2019 Look Like?The Bloomberg Dollar S",
                "publication_date": "2025-04-03T00:00:00.000Z",
                "sentiment": "Negative",
                "sentimentScore": "-0.7269",
                "source": "Bloomberg",
                "ticker": "C",
                "title": "Dollar Drops by Most on Record as Traders Brace for More Pain",
                "url": "https://finance.yahoo.com/news/dollar-slides-concern-trump-tariffs-070440166.html"
            },
            {
                "headline": "(Bloomberg) -- The yield on benchmark Treasuries fell briefly below 4% for the first time since October as Wall Street fretted that the US economy will end up worse off from President Donald Trump\u2019s trade war.Most Read from BloombergMetro-North Is Faster Than Acela on NYC-New Haven Route After Signal UpdatesHousing Agency Aims to Relocate Its DC HeadquartersLocal Governments Vie for Fired Federal WorkersLondon Clears Final Hurdle for More High-Speed Trains to EuropeWhat Would \u2018Transportation Abu",
                "publication_date": "2025-04-03T00:00:00.000Z",
                "sentiment": "Negative",
                "sentimentScore": "-0.6705",
                "source": "Bloomberg",
                "ticker": "C",
                "title": "US 10-Year Yield Drops Below 4% for First Time Since Trump Won",
                "url": "https://finance.yahoo.com/news/us-10-yield-drops-below-140544183.html"
            },
            {
                "headline": "Investing.com -- Citi has made a series of rating adjustments across U.S. retail stocks, reacting to a shifting macro backdrop marked by higher tariffs and rising recession risks.",
                "publication_date": "2025-04-03T00:00:00.000Z",
                "sentiment": "Negative",
                "sentimentScore": "-0.5994",
                "source": "Investing.com",
                "ticker": "C",
                "title": "Citi reshuffles U.S. retail stock ratings after reciprocal tariff announcement",
                "url": "https://finance.yahoo.com/news/citi-reshuffles-u-retail-stock-125540144.html"
            }
        ],
        "avgScore": -0.564625,
        "pctChange": -0.07803327880222014
    },
    "4 1 2025": {
        "importantArticles": [
            {
                "headline": "In the most recent trading session, Citigroup (C) closed at $70.99, indicating a +0.94% shift from the previous trading day.",
                "publication_date": "2025-04-01T00:00:00.000Z",
                "sentiment": "Neutral",
                "sentimentScore": "0.0",
                "source": "Zacks",
                "ticker": "C",
                "title": "Citigroup (C) Outperforms Broader Market: What You Need to Know",
                "url": "https://finance.yahoo.com/news/citigroup-c-outperforms-broader-market-215015772.html"
            },
            {
                "headline": "Citigroup (C) and JPMorgan Chase (JPM) are struggling to find investors for a $900 million leveraged",
                "publication_date": "2025-04-01T00:00:00.000Z",
                "sentiment": "Negative",
                "sentimentScore": "-0.4215",
                "source": "MT Newswires",
                "ticker": "C",
                "title": "Market Chatter: Citigroup, JPMorgan Impacted by Tariffs on Auto Parts Acquisition Backed by Apollo",
                "url": "https://finance.yahoo.com/news/market-chatter-citigroup-jpmorgan-impacted-133704626.html"
            },
            {
                "headline": "(Bloomberg) -- Goldman Sachs Group Inc. strategists cut their targets on European stocks due to the expected hit from President Donald Trump\u2019s tariffs, making a contrarian bet at a time when the region has beaten US peers by a record.Most Read from BloombergWhat Frank Lloyd Wright Learned From the DesertGold-Rush Fever Returns to Historic New Zealand Mining TownBank Regulators Fight for Desks as OCC Returns to New York TowerLondon Clears Final Hurdle for More High-Speed Trains to EuropeThe team",
                "publication_date": "2025-04-01T00:00:00.000Z",
                "sentiment": "Negative",
                "sentimentScore": "-0.7351",
                "source": "Bloomberg",
                "ticker": "C",
                "title": "Goldman Strategists Cut European Stock Targets on US Tariff Threat",
                "url": "https://finance.yahoo.com/news/goldman-strategists-cut-european-stock-084211659.html"
            },
            {
                "headline": "(Bloomberg) -- Goldman Sachs Group Inc. strategists cut their targets on European stocks due to the expected hit from President Donald Trump\u2019s tariffs, making a contrarian bet at a time when the region has beaten US peers by a record.Most Read from BloombergWhat Frank Lloyd Wright Learned From the DesertGold-Rush Fever Returns to Historic New Zealand Mining TownBank Regulators Fight for Desks as OCC Returns to New York TowerLondon Clears Final Hurdle for More High-Speed Trains to EuropeThe team",
                "publication_date": "2025-04-01T00:00:00.000Z",
                "sentiment": "Negative",
                "sentimentScore": "-0.7351",
                "source": "Bloomberg",
                "ticker": "C",
                "title": "Goldman Strategists Cut European Stock Targets on US Tariff Threat",
                "url": "https://finance.yahoo.com/news/goldman-strategists-cut-european-stock-084211659.html"
            },
            {
                "headline": "Citigroup (C) and JPMorgan Chase (JPM) are struggling to find investors for a $900 million leveraged",
                "publication_date": "2025-04-01T00:00:00.000Z",
                "sentiment": "Negative",
                "sentimentScore": "-0.4215",
                "source": "MT Newswires",
                "ticker": "C",
                "title": "Market Chatter: Citigroup, JPMorgan Impacted by Tariffs on Auto Parts Acquisition Backed by Apollo",
                "url": "https://finance.yahoo.com/news/market-chatter-citigroup-jpmorgan-impacted-133704626.html"
            },
            {
                "headline": "In the most recent trading session, Citigroup (C) closed at $70.99, indicating a +0.94% shift from the previous trading day.",
                "publication_date": "2025-04-01T00:00:00.000Z",
                "sentiment": "Neutral",
                "sentimentScore": "0.0",
                "source": "Zacks",
                "ticker": "C",
                "title": "Citigroup (C) Outperforms Broader Market: What You Need to Know",
                "url": "https://finance.yahoo.com/news/citigroup-c-outperforms-broader-market-215015772.html"
            }
        ],
        "avgScore": -0.38553333333333334,
        "pctChange": 0.01729516876763432
    },
    "3 28 2025": {
        "importantArticles": [
            {
                "headline": "Citigroup (NYSE: C) has had a great run over the past six months, rising more than 22% over the span.  There was probably a time when Citigroup's shares were a bargain, but that time doesn't appear to be now.  The stock's performance over the last six months speaks to a company that has clearly been much loved by investors, and that love has had an almost inevitable effect.",
                "publication_date": "2025-03-28T00:00:00.000Z",
                "sentiment": "Positive",
                "sentimentScore": "0.965",
                "source": "Motley Fool",
                "ticker": "C",
                "title": "1 Magnificent High-Yield Bank Stock Down 30% to Buy and Hold Forever",
                "url": "https://finance.yahoo.com/news/1-magnificent-high-yield-bank-083500261.html"
            },
            {
                "headline": "CVS Health, Ulta Beauty, Progressive, AMD and Citigroup are part of the Zacks top Analyst Blog.",
                "publication_date": "2025-03-28T00:00:00.000Z",
                "sentiment": "Positive",
                "sentimentScore": "0.6808",
                "source": "Zacks",
                "ticker": "C",
                "title": "The Zacks Analyst Blog Highlights CVS Health, Ulta Beauty, Progressive, AMD and Citigroup",
                "url": "https://finance.yahoo.com/news/zacks-analyst-blog-highlights-cvs-151600921.html"
            },
            {
                "headline": "Robinhood co-founder and CEO Vlad Tenev turns his sights on getting traditional banking customers.",
                "publication_date": "2025-03-28T00:00:00.000Z",
                "sentiment": "Neutral",
                "sentimentScore": "0.0",
                "source": "Yahoo Finance",
                "ticker": "C",
                "title": "Robinhood is taking on Bank of America, Citigroup, and JPMorgan",
                "url": "https://finance.yahoo.com/news/robinhood-is-taking-on-bank-of-america-citigroup-and-jpmorgan-213031289.html"
            },
            {
                "headline": "(Bloomberg) -- Oil edged higher as signs of tighter near-term supply-and-demand balances overshadowed an intensifying global trade war that threatens to crimp global energy consumption. Most Read from BloombergWhy Did the Government Declare War on My Adorable Tiny Truck?How SUVs Are Making Traffic WorseGold-Rush Fever Returns to Historic New Zealand Mining TownTrump Slashed International Aid. Geneva Is Feeling the Impact.These US Bridges Face High Risk of Catastrophic Ship StrikesWest Texas Inte",
                "publication_date": "2025-03-28T00:00:00.000Z",
                "sentiment": "Negative",
                "sentimentScore": "-0.8957",
                "source": "Bloomberg",
                "ticker": "C",
                "title": "Oil Edges Up as US Stockpile Decline Overshadows Wider Trade War",
                "url": "https://finance.yahoo.com/news/oil-holds-gain-us-posts-233047175.html"
            },
            {
                "headline": "Robinhood co-founder and CEO Vlad Tenev turns his sights on getting traditional banking customers.",
                "publication_date": "2025-03-28T00:00:00.000Z",
                "sentiment": "Neutral",
                "sentimentScore": "0.0",
                "source": "Yahoo Finance",
                "ticker": "C",
                "title": "Robinhood is taking on Bank of America, Citigroup, and JPMorgan",
                "url": "https://finance.yahoo.com/news/robinhood-is-taking-on-bank-of-america-citigroup-and-jpmorgan-213031289.html"
            },
            {
                "headline": "CVS Health, Ulta Beauty, Progressive, AMD and Citigroup are part of the Zacks top Analyst Blog.",
                "publication_date": "2025-03-28T00:00:00.000Z",
                "sentiment": "Positive",
                "sentimentScore": "0.6808",
                "source": "Zacks",
                "ticker": "C",
                "title": "The Zacks Analyst Blog Highlights CVS Health, Ulta Beauty, Progressive, AMD and Citigroup",
                "url": "https://finance.yahoo.com/news/zacks-analyst-blog-highlights-cvs-151600921.html"
            }
        ],
        "avgScore": 0.18752499999999997,
        "pctChange": 0.009384274357055656
    },
    "3 27 2025": {
        "importantArticles": [
            {
                "headline": "Unlock strong returns with these top female-led firms.",
                "publication_date": "2025-03-27T00:00:00.000Z",
                "sentiment": "Positive",
                "sentimentScore": "0.6249",
                "source": "Zacks",
                "ticker": "C",
                "title": "Top Women-Run Company Stocks to Enrich Your Portfolio",
                "url": "https://finance.yahoo.com/news/top-women-run-company-stocks-134900279.html"
            },
            {
                "headline": "(Bloomberg) -- Citigroup Inc. is expanding its investment banking team in Japan as the Wall Street firm bets that the country\u2019s deal fee pool will finally rebound after a two-decade slump.Most Read from BloombergThey Built a Secret Apartment in a Mall. Now the Mall Is Dying.Why Did the Government Declare War on My Adorable Tiny Truck?How SUVs Are Making Traffic WorseTrump Slashed International Aid. Geneva Is Feeling the Impact.These US Bridges Face High Risk of Catastrophic Ship StrikesJapan was",
                "publication_date": "2025-03-27T00:00:00.000Z",
                "sentiment": "Negative",
                "sentimentScore": "-0.7506",
                "source": "Bloomberg",
                "ticker": "C",
                "title": "Citigroup Hiring Dealmakers in Japan With Fee Pool Seen Reviving",
                "url": "https://finance.yahoo.com/news/citigroup-hiring-dealmakers-japan-fee-220000743.html"
            },
            {
                "headline": "(Bloomberg) -- Citigroup Inc. is expanding its investment banking team in Japan as the Wall Street firm bets that the country\u2019s deal fee pool will finally rebound after a two-decade slump.Most Read from BloombergThey Built a Secret Apartment in a Mall. Now the Mall Is Dying.Why Did the Government Declare War on My Adorable Tiny Truck?How SUVs Are Making Traffic WorseTrump Slashed International Aid. Geneva Is Feeling the Impact.These US Bridges Face High Risk of Catastrophic Ship StrikesJapan was",
                "publication_date": "2025-03-27T00:00:00.000Z",
                "sentiment": "Negative",
                "sentimentScore": "-0.7506",
                "source": "Bloomberg",
                "ticker": "C",
                "title": "Citigroup Hiring Dealmakers in Japan With Fee Pool Seen Reviving",
                "url": "https://finance.yahoo.com/news/citigroup-hiring-dealmakers-japan-fee-220000743.html"
            },
            {
                "headline": "Unlock strong returns with these top female-led firms.",
                "publication_date": "2025-03-27T00:00:00.000Z",
                "sentiment": "Positive",
                "sentimentScore": "0.6249",
                "source": "Zacks",
                "ticker": "C",
                "title": "Top Women-Run Company Stocks to Enrich Your Portfolio",
                "url": "https://finance.yahoo.com/news/top-women-run-company-stocks-134900279.html"
            }
        ],
        "avgScore": -0.06285000000000002,
        "pctChange": -0.021155138139827213
    },
    "3 26 2025": {
        "importantArticles": [
            {
                "headline": "Dividends are one of the best benefits to being a shareholder, but finding a great dividend stock is no easy task. Does Citigroup (C) have what it takes? Let's find out.",
                "publication_date": "2025-03-26T00:00:00.000Z",
                "sentiment": "Positive",
                "sentimentScore": "0.9022",
                "source": "Zacks",
                "ticker": "C",
                "title": "Citigroup (C) Could Be a Great Choice",
                "url": "https://finance.yahoo.com/news/citigroup-c-could-great-choice-154511901.html"
            },
            {
                "headline": "NEW YORK (Reuters) -Wall Street banker bonuses rose 31.5% to an average $244,700 last year as dealmaking rebounded, but the boom times may wane as economic uncertainty rises, New York State Comptroller Thomas DiNapoli said on Wednesday.  Deals have slowed this quarter as companies navigate changing policies from President Donald Trump's administration, including tariffs and personnel changes atop regulatory agencies.  \"This financial market strength is good news for New York's economy and our fiscal position, which relies on the tax revenue it generates,\" DiNapoli said in a statement.",
                "publication_date": "2025-03-26T00:00:00.000Z",
                "sentiment": "Positive",
                "sentimentScore": "0.81",
                "source": "Reuters",
                "ticker": "C",
                "title": "Wall Street bonuses jump 32% as total surges to record, NY comptroller says",
                "url": "https://finance.yahoo.com/news/wall-street-bonuses-jump-32-090311966.html"
            },
            {
                "headline": "The largest U.S. banks are facing shareholder votes on a number of politically charged issues \u2014 some backed by conservative groups and others championed by organizations with a more progressive bent.",
                "publication_date": "2025-03-26T00:00:00.000Z",
                "sentiment": "Positive",
                "sentimentScore": "0.2023",
                "source": "American Banker",
                "ticker": "C",
                "title": "Animal welfare, DEI and more: Banks face votes on hot topics",
                "url": "https://finance.yahoo.com/news/animal-welfare-dei-more-banks-201648133.html"
            },
            {
                "headline": "Maeve Bradley believed she was in line for a promotion on her return from maternity leave.",
                "publication_date": "2025-03-26T00:00:00.000Z",
                "sentiment": "Negative",
                "sentimentScore": "-0.0516",
                "source": "PA Media: Money",
                "ticker": "C",
                "title": "Former Citibank employee settles sex discrimination case for \u00a3215,000",
                "url": "https://finance.yahoo.com/news/former-citibank-employee-settles-sex-000100212.html"
            },
            {
                "headline": "In the latest trading session, Citigroup (C) closed at $74.47, marking a +0.58% move from the previous day.",
                "publication_date": "2025-03-26T00:00:00.000Z",
                "sentiment": "Neutral",
                "sentimentScore": "0.0",
                "source": "Zacks",
                "ticker": "C",
                "title": "Why Citigroup (C) Outpaced the Stock Market Today",
                "url": "https://finance.yahoo.com/news/why-citigroup-c-outpaced-stock-215014722.html"
            },
            {
                "headline": "The largest U.S. banks are facing shareholder votes on a number of politically charged issues \u2014 some backed by conservative groups and others championed by organizations with a more progressive bent.",
                "publication_date": "2025-03-26T00:00:00.000Z",
                "sentiment": "Positive",
                "sentimentScore": "0.2023",
                "source": "American Banker",
                "ticker": "C",
                "title": "Animal welfare, DEI and more: Banks face votes on hot topics",
                "url": "https://finance.yahoo.com/news/animal-welfare-dei-more-banks-201648133.html"
            }
        ],
        "avgScore": 0.37258,
        "pctChange": -0.01897869238382439
    },
    "3 25 2025": {
        "importantArticles": [
            {
                "headline": "Citigroup (NYSE:C) gained 5.86% last week, possibly influenced by the announcement on March 25, 2025, where Citi Issuer Services was positioned as depositary bank for Nightingale Health's ADR program. This client announcement occurred alongside broader stock market trends, wherein the S&P 500 and Nasdaq saw slight increases, reflecting a recovering market sentiment. Furthermore, despite several shareholder proposals facing resistance from Citigroup, investor focus remained on the company's...",
                "publication_date": "2025-03-25T00:00:00.000Z",
                "sentiment": "Positive",
                "sentimentScore": "0.3818",
                "source": "Simply Wall St.",
                "ticker": "C",
                "title": "Citigroup (NYSE:C) Sees 6% Rise as Nightingale Health ADR Program Launched",
                "url": "https://finance.yahoo.com/news/citigroup-nyse-c-sees-6-173747636.html"
            },
            {
                "headline": "(Bloomberg) -- Turkish bonds and stocks rebounded as top economic officials sought to reassure foreign investors about last week\u2019s detention of Istanbul Mayor Ekrem Imamoglu, a move that triggered billions of dollars in outflows.Finance Minister Mehmet Simsek promised to do \u201cwhatever it takes\u201d to stabilize financial markets, according to people who joined a teleconference organized by Citigroup Inc. and Deutsche Bank. Officials described the recent market turmoil as a temporary event, they said.",
                "publication_date": "2025-03-25T00:00:00.000Z",
                "sentiment": "Positive",
                "sentimentScore": "0.1779",
                "source": "Bloomberg",
                "ticker": "C",
                "title": "Turkish Assets Rebound as Simsek Vows to Restore Stability",
                "url": "https://finance.yahoo.com/news/turkey-finance-czar-meet-investors-042924351.html"
            },
            {
                "headline": "Frank Bisignano, Donald Trump's pick to lead the Social Security administration, called improving customer service 'a mission critical function' Tuesday even as early Trump administration actions undermined existing service.",
                "publication_date": "2025-03-25T00:00:00.000Z",
                "sentiment": "Positive",
                "sentimentScore": "0.1027",
                "source": "Yahoo Finance",
                "ticker": "C",
                "title": "Trump's Social Security pick promises 'improving service' at agency roiled by upheaval",
                "url": "https://finance.yahoo.com/news/trumps-social-security-pick-promises-improving-service-at-agency-roiled-by-upheaval-174133323.html"
            },
            {
                "headline": "LONDON, March 25, 2025--Citi Issuer Services, acting through Citibank N.A., has been appointed by Nightingale Health OYJ (\"Nightingale Health\") to act as depositary bank for its sponsored Level 1 American Depositary Receipt (\"ADR\") program.",
                "publication_date": "2025-03-25T00:00:00.000Z",
                "sentiment": "Neutral",
                "sentimentScore": "0.0",
                "source": "Business Wire",
                "ticker": "C",
                "title": "Citi Appointed as Depositary Bank for Nightingale Health OYJ\u2019s ADR Program",
                "url": "https://finance.yahoo.com/news/citi-appointed-depositary-bank-nightingale-080000284.html"
            },
            {
                "headline": "Frank Bisignano, Donald Trump's pick to lead the Social Security administration, called improving customer service 'a mission critical function' Tuesday even as early Trump administration actions undermined existing service.",
                "publication_date": "2025-03-25T00:00:00.000Z",
                "sentiment": "Positive",
                "sentimentScore": "0.1027",
                "source": "Yahoo Finance",
                "ticker": "C",
                "title": "Trump's Social Security pick promises 'improving service' at agency roiled by upheaval",
                "url": "https://finance.yahoo.com/news/trumps-social-security-pick-promises-improving-service-at-agency-roiled-by-upheaval-174133323.html"
            },
            {
                "headline": "(Bloomberg) -- Turkish bonds and stocks rebounded as top economic officials sought to reassure foreign investors about last week\u2019s detention of Istanbul Mayor Ekrem Imamoglu, a move that triggered billions of dollars in outflows.Finance Minister Mehmet Simsek promised to do \u201cwhatever it takes\u201d to stabilize financial markets, according to people who joined a teleconference organized by Citigroup Inc. and Deutsche Bank. Officials described the recent market turmoil as a temporary event, they said.",
                "publication_date": "2025-03-25T00:00:00.000Z",
                "sentiment": "Positive",
                "sentimentScore": "0.1779",
                "source": "Bloomberg",
                "ticker": "C",
                "title": "Turkish Assets Rebound as Simsek Vows to Restore Stability",
                "url": "https://finance.yahoo.com/news/turkey-finance-czar-meet-investors-042924351.html"
            }
        ],
        "avgScore": 0.1656,
        "pctChange": -0.01651676294845615
    },
    "coef": 0.1789473684210526,
    "avgCoef": -0.006444146214162915,
    "similar": {
        "VOD": 0.7087719298245614,
        "BP": 0.6614035087719298,
        "AMCR": 0.6403508771929824,
        "PBR": 0.6368421052631579
    }
}