{
    "4 17 2025": {
        "importantArticles": [
            {
                "headline": "STEINHAUSEN, Switzerland, April 16, 2025 (GLOBE NEWSWIRE) -- Transocean Ltd. (NYSE: RIG) today issued a quarterly Fleet Status Report that provides the current status of, and contract information for, the company\u2019s fleet of offshore drilling rigs. As of April 16, 2025, the company\u2019s total backlog is approximately $7.9 billion. The report can be accessed on the company\u2019s website: www.deepwater.com. About Transocean Transocean is a leading international provider of offshore contract drilling servi",
                "publication_date": "2025-04-17T00:00:00.000Z",
                "sentiment": "Neutral",
                "sentimentScore": "0.0",
                "source": "GlobeNewswire",
                "ticker": "RIG",
                "title": "Transocean Ltd. Provides Quarterly Fleet Status Report",
                "url": "https://finance.yahoo.com/news/transocean-ltd-provides-quarterly-fleet-202900065.html"
            },
            {
                "headline": "STEINHAUSEN, Switzerland, April 16, 2025 (GLOBE NEWSWIRE) -- Transocean Ltd. (NYSE: RIG) today issued a quarterly Fleet Status Report that provides the current status of, and contract information for, the company\u2019s fleet of offshore drilling rigs. As of April 16, 2025, the company\u2019s total backlog is approximately $7.9 billion. The report can be accessed on the company\u2019s website: www.deepwater.com. About Transocean Transocean is a leading international provider of offshore contract drilling servi",
                "publication_date": "2025-04-17T00:00:00.000Z",
                "sentiment": "Neutral",
                "sentimentScore": "0.0",
                "source": "GlobeNewswire",
                "ticker": "RIG",
                "title": "Transocean Ltd. Provides Quarterly Fleet Status Report",
                "url": "https://finance.yahoo.com/news/transocean-ltd-provides-quarterly-fleet-202900065.html"
            }
        ],
        "avgScore": 0.0
    },
    "4 11 2025": {
        "importantArticles": [
            {
                "headline": "STEINHAUSEN, Switzerland, April 10, 2025 (GLOBE NEWSWIRE) -- Transocean Ltd. (NYSE: RIG) announced today that it will report earnings for the first quarter 2025 on Monday, April 28, 2025. The company will conduct a teleconference to discuss the results starting at 9 a.m. EDT, 3 p.m. CEST, on Tuesday, April 29, 2025. Individuals who wish to participate should dial +1 785-424-1619 approximately 15 minutes prior to the scheduled start time and refer to conference code 119877. The teleconference wil",
                "publication_date": "2025-04-11T00:00:00.000Z",
                "sentiment": "Positive",
                "sentimentScore": "0.4019",
                "source": "GlobeNewswire",
                "ticker": "RIG",
                "title": "Transocean Ltd. Announces First Quarter 2025 Earnings Release Date",
                "url": "https://finance.yahoo.com/news/transocean-ltd-announces-first-quarter-203100914.html"
            },
            {
                "headline": "STEINHAUSEN, Switzerland, April 10, 2025 (GLOBE NEWSWIRE) -- Transocean Ltd. (NYSE: RIG) announced today that it will report earnings for the first quarter 2025 on Monday, April 28, 2025. The company will conduct a teleconference to discuss the results starting at 9 a.m. EDT, 3 p.m. CEST, on Tuesday, April 29, 2025. Individuals who wish to participate should dial +1 785-424-1619 approximately 15 minutes prior to the scheduled start time and refer to conference code 119877. The teleconference wil",
                "publication_date": "2025-04-11T00:00:00.000Z",
                "sentiment": "Positive",
                "sentimentScore": "0.4019",
                "source": "GlobeNewswire",
                "ticker": "RIG",
                "title": "Transocean Ltd. Announces First Quarter 2025 Earnings Release Date",
                "url": "https://finance.yahoo.com/news/transocean-ltd-announces-first-quarter-203100914.html"
            }
        ],
        "avgScore": 0.4019
    },
    "4 8 2025": {
        "importantArticles": [
            {
                "headline": "We recently published a list of AI Stocks Dominate Monday\u2019s Top 10 Performers. In this article, we are going to take a look at where Transocean Ltd. (NYSE:RIG) stands against other AI stocks that dominate Monday\u2019s top performers. The stock market finished mixed on Monday as investors remained cautious over the escalating trade tensions globally, [\u2026]",
                "publication_date": "2025-04-08T00:00:00.000Z",
                "sentiment": "Negative",
                "sentimentScore": "-0.3612",
                "source": "Insider Monkey",
                "ticker": "RIG",
                "title": "Why Transocean Ltd. (RIG) Went Up On Monday?",
                "url": "https://finance.yahoo.com/news/why-transocean-ltd-rig-went-102016689.html"
            },
            {
                "headline": "We recently published a list of AI Stocks Dominate Monday\u2019s Top 10 Performers. In this article, we are going to take a look at where Transocean Ltd. (NYSE:RIG) stands against other AI stocks that dominate Monday\u2019s top performers. The stock market finished mixed on Monday as investors remained cautious over the escalating trade tensions globally, [\u2026]",
                "publication_date": "2025-04-08T00:00:00.000Z",
                "sentiment": "Negative",
                "sentimentScore": "-0.3612",
                "source": "Insider Monkey",
                "ticker": "RIG",
                "title": "Why Transocean Ltd. (RIG) Went Up On Monday?",
                "url": "https://finance.yahoo.com/news/why-transocean-ltd-rig-went-102016689.html"
            }
        ],
        "avgScore": -0.3612
    },
    "3 25 2025": {
        "importantArticles": [
            {
                "headline": "Following a careful analysis of the Zacks Oil and Gas - Drilling industry, we advise focusing on companies like PTEN, RIG and HP.",
                "publication_date": "2025-03-25T00:00:00.000Z",
                "sentiment": "Positive",
                "sentimentScore": "0.2185",
                "source": "Zacks",
                "ticker": "RIG",
                "title": "3 Oil & Gas Drilling Stocks Navigating a Volatile Market",
                "url": "https://finance.yahoo.com/news/3-oil-gas-drilling-stocks-151900927.html"
            },
            {
                "headline": "RIG holds a strong position in offshore drilling with high demand and innovative technology, but its high debt and financial losses could affect growth prospects.",
                "publication_date": "2025-03-25T00:00:00.000Z",
                "sentiment": "Positive",
                "sentimentScore": "0.1614",
                "source": "Zacks",
                "ticker": "RIG",
                "title": "Here's Why Retain Strategy is Apt for Transocean Stock Now",
                "url": "https://finance.yahoo.com/news/heres-why-retain-strategy-apt-095900034.html"
            },
            {
                "headline": "RIG holds a strong position in offshore drilling with high demand and innovative technology, but its high debt and financial losses could affect growth prospects.",
                "publication_date": "2025-03-25T00:00:00.000Z",
                "sentiment": "Positive",
                "sentimentScore": "0.1614",
                "source": "Zacks",
                "ticker": "RIG",
                "title": "Here's Why Retain Strategy is Apt for Transocean Stock Now",
                "url": "https://finance.yahoo.com/news/heres-why-retain-strategy-apt-095900034.html"
            },
            {
                "headline": "Following a careful analysis of the Zacks Oil and Gas - Drilling industry, we advise focusing on companies like PTEN, RIG and HP.",
                "publication_date": "2025-03-25T00:00:00.000Z",
                "sentiment": "Positive",
                "sentimentScore": "0.2185",
                "source": "Zacks",
                "ticker": "RIG",
                "title": "3 Oil & Gas Drilling Stocks Navigating a Volatile Market",
                "url": "https://finance.yahoo.com/news/3-oil-gas-drilling-stocks-151900927.html"
            }
        ],
        "avgScore": 0.18995
    },
    "3 19 2025": {
        "importantArticles": [
            {
                "headline": "Transocean (RIG) reported earnings 30 days ago. What's next for the stock? We take a look at earnings estimates for some clues.",
                "publication_date": "2025-03-19T00:00:00.000Z",
                "sentiment": "Neutral",
                "sentimentScore": "0.0",
                "source": "Zacks",
                "ticker": "RIG",
                "title": "Why Is Transocean (RIG) Down 9.9% Since Last Earnings Report?",
                "url": "https://finance.yahoo.com/news/why-transocean-rig-down-9-153003119.html"
            },
            {
                "headline": "Transocean (RIG) reported earnings 30 days ago. What's next for the stock? We take a look at earnings estimates for some clues.",
                "publication_date": "2025-03-19T00:00:00.000Z",
                "sentiment": "Neutral",
                "sentimentScore": "0.0",
                "source": "Zacks",
                "ticker": "RIG",
                "title": "Why Is Transocean (RIG) Down 9.9% Since Last Earnings Report?",
                "url": "https://finance.yahoo.com/news/why-transocean-rig-down-9-153003119.html"
            }
        ],
        "avgScore": 0.0
    },
    "coef": -0.9746794344808963,
    "avgCoef": 0.10948167658711119,
    "similar": {
        "T": 0.8207826816681234,
        "BABA": 0.35909242322980395,
        "KVUE": 0.35909242322980395,
        "MP": 0.20519567041703085
    }
}